.editorconfig
.pre-commit-config.yaml
CHANGELOG.rst
CONTRIBUTING.rst
LICENSE
Makefile
README.rst
example.json
extremitypathfinder/__init__.py
extremitypathfinder/command_line.py
extremitypathfinder/configs.py
extremitypathfinder/extremitypathfinder.py
extremitypathfinder/numba_replacements.py
extremitypathfinder/plotting.py
extremitypathfinder/types.py
extremitypathfinder/utils.py
extremitypathfinder/utils_numba.py
tests/__init__.py
tests/cli_test.py
tests/helper_fcts_test.py
tests/helpers.py
tests/main_test.py
tests/test_cases.py
tests/test_find_visible.py
tox.ini
extremitypathfinder-2.7.1.dist-info/LICENSE
extremitypathfinder-2.7.1.dist-info/METADATA
extremitypathfinder-2.7.1.dist-info/WHEEL
extremitypathfinder-2.7.1.dist-info/entry_points.txt
extremitypathfinder-2.7.1.dist-info/RECORD
