Metadata-Version: 2.1
Name: extremitypathfinder
Version: 2.7.1
Summary: python package for fast shortest path computation on 2D polygon or grid maps
Home-page: https://extremitypathfinder.readthedocs.io/en/latest/
License: MIT
Keywords: path-planning,path-finding,shortest-path,visibility,graph,polygon,grid,map,robotics,navigation,offline
Author: jannikmi
Author-email: github@michelfe.it
Requires-Python: >=3.8,<3.12
Classifier: Development Status :: 5 - Production/Stable
Classifier: Intended Audience :: Developers
Classifier: Intended Audience :: Information Technology
Classifier: Intended Audience :: Science/Research
Classifier: License :: OSI Approved :: MIT License
Classifier: Natural Language :: English
Classifier: Operating System :: OS Independent
Classifier: Programming Language :: Python :: 3
Classifier: Programming Language :: Python :: 3.8
Classifier: Programming Language :: Python :: 3.9
Classifier: Programming Language :: Python :: 3.10
Classifier: Programming Language :: Python :: 3.11
Classifier: Topic :: Education
Classifier: Topic :: Games/Entertainment
Classifier: Topic :: Scientific/Engineering
Classifier: Topic :: Scientific/Engineering :: Artificial Intelligence
Provides-Extra: docs
Provides-Extra: numba
Provides-Extra: plot
Provides-Extra: test
Requires-Dist: networkx (>=3,<4)
Requires-Dist: numba (>=0.56.0,<0.57.0) ; extra == "numba"
Requires-Dist: numpy (>=1.22,<2.0)
Requires-Dist: scipy (>=1.10.1,<2.0.0) ; extra == "numba"
Project-URL: Documentation, https://extremitypathfinder.readthedocs.io/en/latest/
Project-URL: Repository, https://github.com/jannikmi/extremitypathfinder
